datasetGPT/__init__.py
datasetGPT/__main__.py
datasetGPT/base.py
datasetGPT/cli.py
datasetGPT/conversations.py
datasetGPT/outputs.py
datasetGPT/texts.py
datasetGPT-0.0.4.dist-info/METADATA
datasetGPT-0.0.4.dist-info/WHEEL
datasetGPT-0.0.4.dist-info/entry_points.txt
datasetGPT-0.0.4.dist-info/top_level.txt
datasetGPT-0.0.4.dist-info/RECORD
