Metadata-Version: 2.1
Name: datasetGPT
Version: 0.0.4
Summary: Generate textual and conversational datasets with LLMs.
Home-page: https://github.com/radi-cho/datasetGPT
Author: Radostin Cholakov
Author-email: radicho123@gmail.com
Keywords: dataset,llm,langchain,openai
Requires-Dist: langchain >=0.0.113
Requires-Dist: click >=8.1
